adetailer/__init__.py
adetailer/__version__.py
adetailer/args.py
adetailer/common.py
adetailer/mask.py
adetailer/mediapipe.py
adetailer/opts.py
adetailer/ultralytics.py
adetailer-24.9.0.dist-info/METADATA
adetailer-24.9.0.dist-info/WHEEL
adetailer-24.9.0.dist-info/licenses/LICENSE.md
adetailer-24.9.0.dist-info/RECORD
