Metadata-Version: 2.3
Name: adetailer
Version: 24.9.0
Summary: An object detection and auto-mask extension for stable diffusion webui.
Project-URL: repository, https://github.com/Bing-su/adetailer
Author-email: dowon <ks2515@naver.com>
License: AGPL-3.0
License-File: LICENSE.md
Keywords: adetailer,stable-diffusion,stable-diffusion-webui,ultralytics
Classifier: License :: OSI Approved :: GNU Affero General Public License v3
Classifier: Topic :: Scientific/Engineering :: Image Recognition
Requires-Python: >=3.9
Requires-Dist: huggingface-hub
Requires-Dist: mediapipe>=0.10.13
Requires-Dist: pydantic<3
Requires-Dist: rich>=13
Requires-Dist: ultralytics>=8.2
Provides-Extra: dev
Requires-Dist: devtools; extra == 'dev'
Requires-Dist: pre-commit; extra == 'dev'
Requires-Dist: ruff; extra == 'dev'
Provides-Extra: test
Requires-Dist: hypothesis; extra == 'test'
Requires-Dist: pytest; extra == 'test'
